llama_index/readers/zep/__init__.py
llama_index/readers/zep/base.py
llama_index_readers_zep-0.4.1.dist-info/METADATA
llama_index_readers_zep-0.4.1.dist-info/WHEEL
llama_index_readers_zep-0.4.1.dist-info/licenses/LICENSE
llama_index_readers_zep-0.4.1.dist-info/RECORD
