Metadata-Version: 2.4
Name: llama-index-readers-zep
Version: 0.4.1
Summary: llama-index readers zep integration
Author-email: Your Name <you@example.com>
Maintainer: zep
License-Expression: MIT
License-File: LICENSE
Keywords: memory,retriever,storage,zep
Requires-Python: <4.0,>=3.9.0
Requires-Dist: llama-index-core<0.15,>=0.13.0
Requires-Dist: zep-python<2,>=1.5.0
